mippy/__init__.py
mippy/application.py
mippy/fileio.py
mippy/html.py
mippy/improcess.py
mippy/launcher.py
mippy/math.py
mippy/misc.py
mippy/mlogging.py
mippy/splash.py
mippy/threading.py
mippy/viewing.py
mippy/luts/16_colors.csv
mippy/luts/blue.csv
mippy/luts/colours_roman.csv
mippy/luts/cyan.csv
mippy/luts/fire.csv
mippy/luts/green.csv
mippy/luts/green_fire_blue.csv
mippy/luts/hi_lo.csv
mippy/luts/ice.csv
mippy/luts/magenta.csv
mippy/luts/phase.csv
mippy/luts/physics.csv
mippy/luts/rainbow.csv
mippy/luts/red.csv
mippy/luts/red_green.csv
mippy/luts/red_grey_green.csv
mippy/luts/red_grey_green_clipped.csv
mippy/luts/spectrum.csv
mippy/luts/yellow.csv
mippy/mdicom/__init__.py
mippy/mdicom/anon.py
mippy/mdicom/io.py
mippy/mdicom/mrenhanced.py
mippy/mdicom/mrspectroscopy.py
mippy/mdicom/pixel.py
mippy/mdicom/reading.py
mippy/mdicom/siemens.py
mippy/mdicom/sorting.py
mippy/mdicom/xml.py
mippy/mdicom/miners/SIEMENS.py
mippy/mdicom/miners/__init__.py
mippy/mdicom/miners/ge_fallback.py
mippy/mdicom/miners/implementations.py
mippy/mdicom/miners/philips_fallback.py
mippy/mdicom/miners/siemens_fallback.py
mippy/mdicom/miners/syngo_mr_xa20a.py
mippy/mdicom/miners/syngo_mr_xa31a.py
mippy/mviewer/__init__.py
mippy/mviewer/config
mippy/mviewer/module_main.py
mippy/resources/add.png
mippy/resources/brain_bw.xbm
mippy/resources/brain_orange.ico
mippy/resources/common.png
mippy/resources/dcmdjpeg_linux
mippy/resources/dcmdjpeg_mac
mippy/resources/dcmdjpeg_win.exe
mippy/resources/ellipse_roi.png
mippy/resources/freehand_roi.png
mippy/resources/line_roi.png
mippy/resources/mrs.png
mippy/resources/roi_circle.png
mippy/resources/roi_ellipse.png
mippy/resources/roi_freehand.png
mippy/resources/roi_line.png
mippy/resources/roi_rectangular.png
mippy/resources/roi_rectangular_ab.png
mippy/resources/splash11.jpg
mippy/resources/splash20.bmp
mippy/resources/splash20.jpg
mippy/resources/splash3.jpg
mippy/resources/square_roi.png
mippy/resources/subtract.png
mippy-2.22.3.data/scripts/_mippy.py
mippy-2.22.3.dist-info/licenses/LICENSE
mippy-2.22.3.dist-info/METADATA
mippy-2.22.3.dist-info/WHEEL
mippy-2.22.3.dist-info/top_level.txt
mippy-2.22.3.dist-info/RECORD
