Metadata-Version: 2.4
Name: mippy
Version: 2.22.3
Summary: Modular Image Processing in Python
Home-page: https://gitlab.com/rbf906/mippy
Author: Robert Flintham
Author-email: rbf906@gmail.com
License: BSD-3-Clause
Classifier: Programming Language :: Python :: 3
Requires-Python: ==3.13.*
License-File: LICENSE
Requires-Dist: numpy
Requires-Dist: scipy
Requires-Dist: pydicom
Requires-Dist: pillow
Requires-Dist: nibabel
Requires-Dist: easygui
Requires-Dist: dill
Requires-Dist: tinydb<4
Requires-Dist: requests
Requires-Dist: tkinterhtml
Requires-Dist: markdown2
Requires-Dist: matplotlib
Requires-Dist: scikit-image
Requires-Dist: pyperclip
Requires-Dist: colorama
Requires-Dist: termcolor
Requires-Dist: psutil
Requires-Dist: pyscreenshot
Requires-Dist: threadpoolctl
Requires-Dist: setuptools
Dynamic: author
Dynamic: author-email
Dynamic: classifier
Dynamic: home-page
Dynamic: license
Dynamic: license-file
Dynamic: requires-dist
Dynamic: requires-python
Dynamic: summary
